divyanshi_iq_library/__init__.py
divyanshi_iq_library/divyanshi_iq_library.py
divyanshi_iq_library-0.1.dist-info/METADATA
divyanshi_iq_library-0.1.dist-info/WHEEL
divyanshi_iq_library-0.1.dist-info/top_level.txt
divyanshi_iq_library-0.1.dist-info/RECORD
